odoo/addons/agreement_helpdesk_mgmt_fieldservice/README.rst
odoo/addons/agreement_helpdesk_mgmt_fieldservice/__init__.py
odoo/addons/agreement_helpdesk_mgmt_fieldservice/__manifest__.py
odoo/addons/agreement_helpdesk_mgmt_fieldservice/i18n/agreement_helpdesk_mgmt_fieldservice.pot
odoo/addons/agreement_helpdesk_mgmt_fieldservice/i18n/it.po
odoo/addons/agreement_helpdesk_mgmt_fieldservice/i18n/sv.po
odoo/addons/agreement_helpdesk_mgmt_fieldservice/models/__init__.py
odoo/addons/agreement_helpdesk_mgmt_fieldservice/models/helpdesk_ticket.py
odoo/addons/agreement_helpdesk_mgmt_fieldservice/readme/CONTRIBUTORS.md
odoo/addons/agreement_helpdesk_mgmt_fieldservice/readme/DESCRIPTION.md
odoo/addons/agreement_helpdesk_mgmt_fieldservice/static/description/icon.png
odoo/addons/agreement_helpdesk_mgmt_fieldservice/static/description/index.html
odoo/addons/agreement_helpdesk_mgmt_fieldservice/tests/__init__.py
odoo/addons/agreement_helpdesk_mgmt_fieldservice/tests/test_helpdesk_ticket_fsm_order_agreement.py
odoo_addon_agreement_helpdesk_mgmt_fieldservice-18.0.1.0.0.6.dist-info/METADATA
odoo_addon_agreement_helpdesk_mgmt_fieldservice-18.0.1.0.0.6.dist-info/WHEEL
odoo_addon_agreement_helpdesk_mgmt_fieldservice-18.0.1.0.0.6.dist-info/top_level.txt
odoo_addon_agreement_helpdesk_mgmt_fieldservice-18.0.1.0.0.6.dist-info/RECORD
